dgi/__init__.py
dgi/cli.py
dgi/code2graph/__init__.py
dgi/code2graph/abstract_graph_builder.py
dgi/code2graph/class_graph_builder.py
dgi/code2graph/method_graph_builder.py
dgi/code2graph/process_facts.py
dgi/code2graph/etc/__init__.py
dgi/code2graph/etc/config.yml
dgi/models/__init__.py
dgi/models/entities.py
dgi/models/relationships.py
dgi/partitioning/__init__.py
dgi/partitioning/partition.py
dgi/schema2graph/__init__.py
dgi/schema2graph/schema_loader.py
dgi/tx2graph/__init__.py
dgi/tx2graph/abstract_transaction_loader.py
dgi/tx2graph/class_transaction_loader.py
dgi/tx2graph/method_transaction_loader.py
dgi/tx2graph/utils/__init__.py
dgi/tx2graph/utils/peg.py
dgi/tx2graph/utils/sqlparse.py
dgi/utils/__init__.py
dgi/utils/logging.py
dgi/utils/parse_config.py
dgi/utils/progress_bar_factory.py
tackle_dgi-1.0.0.dist-info/LICENSE
tackle_dgi-1.0.0.dist-info/METADATA
tackle_dgi-1.0.0.dist-info/WHEEL
tackle_dgi-1.0.0.dist-info/entry_points.txt
tackle_dgi-1.0.0.dist-info/top_level.txt
tackle_dgi-1.0.0.dist-info/RECORD
