Metadata-Version: 2.1
Name: tackle-dgi
Version: 1.0.0
Summary: Konveyor Tackle Data Gravity Insights
Home-page: https://github.com/konveyor/tackle-data-gravity-insights
Author: IBM
License: UNKNOWN
Platform: UNKNOWN
Classifier: Development Status :: 4 - Beta
Classifier: Environment :: Console
Classifier: Intended Audience :: Developers
Classifier: License :: OSI Approved :: Apache Software License
Classifier: Operating System :: OS Independent
Classifier: Programming Language :: Python
Classifier: Programming Language :: Python :: 3
Classifier: Programming Language :: Python :: 3.9
License-File: LICENSE
Requires-Dist: Click (==8.1.3)
Requires-Dist: neomodel (==4.0.10)
Requires-Dist: simple-ddl-parser (==0.25.0)
Requires-Dist: PyYAML (==6.0)
Requires-Dist: ipdb (==0.13.11)
Requires-Dist: pandas (==1.5.3)
Requires-Dist: tqdm (==4.65.0)
Requires-Dist: rich (==13.3.2)
Requires-Dist: rich-click (==1.6.1)
Requires-Dist: py2neo (==2021.2.3)
Requires-Dist: minerva-cargo (==1.1.0)
Provides-Extra: dev
Requires-Dist: nose (==1.3.7) ; extra == 'dev'
Requires-Dist: pinocchio (==0.4.3) ; extra == 'dev'
Requires-Dist: coverage (==7.1.0) ; extra == 'dev'
Requires-Dist: pylint (==2.16.2) ; extra == 'dev'
Requires-Dist: py2neo (==2021.2.3) ; extra == 'dev'
Requires-Dist: flake8 (==6.0.0) ; extra == 'dev'
Requires-Dist: black (==23.1.0) ; extra == 'dev'
Requires-Dist: tox (==3.24.5) ; extra == 'dev'
